{
  "inputs": {
    "node_modules/element-notifier/esm/index.js": {
      "bytes": 1705,
      "imports": []
    },
    "node_modules/qsa-observer/esm/index.js": {
      "bytes": 2089,
      "imports": [
        {
          "path": "node_modules/element-notifier/esm/index.js",
          "kind": "import-statement"
        }
      ]
    },
    "src/utils/map.js": {
      "bytes": 832,
      "imports": []
    },
    "src/utils/str.js": {
      "bytes": 2484,
      "imports": [
        {
          "path": "src/utils/misc.js",
          "kind": "import-statement"
        }
      ]
    },
    "src/utils/attrs.js": {
      "bytes": 5347,
      "imports": [
        {
          "path": "src/utils/misc.js",
          "kind": "import-statement"
        },
        {
          "path": "src/utils/str.js",
          "kind": "import-statement"
        }
      ]
    },
    "src/utils/events.js": {
      "bytes": 3571,
      "imports": [
        {
          "path": "src/utils/misc.js",
          "kind": "import-statement"
        }
      ]
    },
    "src/utils/query.js": {
      "bytes": 1093,
      "imports": []
    },
    "src/utils/misc.js": {
      "bytes": 13575,
      "imports": [
        {
          "path": "src/utils/attrs.js",
          "kind": "import-statement"
        },
        {
          "path": "src/utils/events.js",
          "kind": "import-statement"
        },
        {
          "path": "src/utils/query.js",
          "kind": "import-statement"
        },
        {
          "path": "src/utils/str.js",
          "kind": "import-statement"
        }
      ]
    },
    "src/utils/lazy.js": {
      "bytes": 1242,
      "imports": [
        {
          "path": "src/utils/map.js",
          "kind": "import-statement"
        },
        {
          "path": "src/utils/misc.js",
          "kind": "import-statement"
        }
      ]
    },
    "src/dynamicBehaviour.js": {
      "bytes": 3412,
      "imports": [
        {
          "path": "node_modules/qsa-observer/esm/index.js",
          "kind": "import-statement"
        },
        {
          "path": "src/utils/lazy.js",
          "kind": "import-statement"
        },
        {
          "path": "src/utils/map.js",
          "kind": "import-statement"
        },
        {
          "path": "src/utils/query.js",
          "kind": "import-statement"
        },
        {
          "path": "src/utils/attrs.js",
          "kind": "import-statement"
        }
      ]
    },
    "src/addDialogPolyfill.js": {
      "bytes": 1554,
      "imports": [
        {
          "path": "src/dynamicBehaviour.js",
          "kind": "import-statement"
        },
        {
          "path": "src/utils/attrs.js",
          "kind": "import-statement"
        },
        {
          "path": "src/utils/misc.js",
          "kind": "import-statement"
        }
      ]
    },
    "src/button-dialog.js": {
      "bytes": 3957,
      "imports": [
        {
          "path": "src/utils/attrs.js",
          "kind": "import-statement"
        },
        {
          "path": "src/utils/events.js",
          "kind": "import-statement"
        },
        {
          "path": "src/utils/query.js",
          "kind": "import-statement"
        },
        {
          "path": "src/utils/misc.js",
          "kind": "import-statement"
        },
        {
          "path": "src/dynamicBehaviour.js",
          "kind": "import-statement"
        }
      ]
    },
    "builds/dialog.js": {
      "bytes": 439,
      "imports": [
        {
          "path": "src/addDialogPolyfill.js",
          "kind": "import-statement"
        },
        {
          "path": "src/button-dialog.js",
          "kind": "import-statement"
        },
        {
          "path": "src/dynamicBehaviour.js",
          "kind": "import-statement"
        }
      ]
    },
    "src/utils/date.js": {
      "bytes": 8936,
      "imports": [
        {
          "path": "src/utils/misc.js",
          "kind": "import-statement"
        },
        {
          "path": "src/utils/str.js",
          "kind": "import-statement"
        }
      ]
    },
    "src/time-datetime.js": {
      "bytes": 4435,
      "imports": [
        {
          "path": "src/utils/attrs.js",
          "kind": "import-statement"
        },
        {
          "path": "src/utils/date.js",
          "kind": "import-statement"
        },
        {
          "path": "src/utils/misc.js",
          "kind": "import-statement"
        },
        {
          "path": "src/dynamicBehaviour.js",
          "kind": "import-statement"
        },
        {
          "path": "src/utils/map.js",
          "kind": "import-statement"
        }
      ]
    },
    "src/span-number.js": {
      "bytes": 1777,
      "imports": [
        {
          "path": "src/utils/attrs.js",
          "kind": "import-statement"
        },
        {
          "path": "src/utils/misc.js",
          "kind": "import-statement"
        },
        {
          "path": "src/dynamicBehaviour.js",
          "kind": "import-statement"
        },
        {
          "path": "src/utils/map.js",
          "kind": "import-statement"
        }
      ]
    },
    "builds/formatters.js": {
      "bytes": 306,
      "imports": [
        {
          "path": "src/time-datetime.js",
          "kind": "import-statement"
        },
        {
          "path": "src/span-number.js",
          "kind": "import-statement"
        },
        {
          "path": "src/dynamicBehaviour.js",
          "kind": "import-statement"
        }
      ]
    },
    "src/behaviour.js": {
      "bytes": 1901,
      "imports": [
        {
          "path": "src/dynamicBehaviour.js",
          "kind": "import-statement"
        },
        {
          "path": "src/utils/misc.js",
          "kind": "import-statement"
        },
        {
          "path": "src/utils/map.js",
          "kind": "import-statement"
        },
        {
          "path": "src/utils/events.js",
          "kind": "import-statement"
        }
      ]
    },
    "node_modules/custom-function/esm/factory.js": {
      "bytes": 651,
      "imports": []
    },
    "node_modules/nonchalance/esm/upgrade.js": {
      "bytes": 3001,
      "imports": []
    },
    "node_modules/nonchalance/esm/ce.js": {
      "bytes": 11566,
      "imports": [
        {
          "path": "node_modules/custom-function/esm/factory.js",
          "kind": "import-statement"
        },
        {
          "path": "node_modules/nonchalance/esm/upgrade.js",
          "kind": "import-statement"
        }
      ]
    },
    "node_modules/nonchalance/esm/selector.js": {
      "bytes": 539,
      "imports": [
        {
          "path": "node_modules/qsa-observer/esm/index.js",
          "kind": "import-statement"
        }
      ]
    },
    "src/button-toggle.js": {
      "bytes": 3656,
      "imports": [
        {
          "path": "node_modules/nonchalance/esm/ce.js",
          "kind": "import-statement"
        },
        {
          "path": "node_modules/nonchalance/esm/selector.js",
          "kind": "import-statement"
        },
        {
          "path": "src/utils/events.js",
          "kind": "import-statement"
        },
        {
          "path": "src/utils/attrs.js",
          "kind": "import-statement"
        },
        {
          "path": "src/utils/misc.js",
          "kind": "import-statement"
        },
        {
          "path": "src/utils/query.js",
          "kind": "import-statement"
        }
      ]
    },
    "src/utils/floating.js": {
      "bytes": 11584,
      "imports": [
        {
          "path": "src/utils/attrs.js",
          "kind": "import-statement"
        },
        {
          "path": "src/utils/events.js",
          "kind": "import-statement"
        },
        {
          "path": "src/utils/misc.js",
          "kind": "import-statement"
        }
      ]
    },
    "src/button-dropdown.js": {
      "bytes": 7110,
      "imports": [
        {
          "path": "node_modules/nonchalance/esm/ce.js",
          "kind": "import-statement"
        },
        {
          "path": "node_modules/nonchalance/esm/selector.js",
          "kind": "import-statement"
        },
        {
          "path": "src/utils/events.js",
          "kind": "import-statement"
        },
        {
          "path": "src/utils/attrs.js",
          "kind": "import-statement"
        },
        {
          "path": "src/utils/floating.js",
          "kind": "import-statement"
        },
        {
          "path": "src/utils/misc.js",
          "kind": "import-statement"
        },
        {
          "path": "src/utils/query.js",
          "kind": "import-statement"
        },
        {
          "path": "src/utils/map.js",
          "kind": "import-statement"
        }
      ]
    },
    "src/input-limited.js": {
      "bytes": 5097,
      "imports": [
        {
          "path": "src/utils/events.js",
          "kind": "import-statement"
        },
        {
          "path": "src/utils/str.js",
          "kind": "import-statement"
        },
        {
          "path": "src/dynamicBehaviour.js",
          "kind": "import-statement"
        },
        {
          "path": "src/utils/attrs.js",
          "kind": "import-statement"
        },
        {
          "path": "src/utils/misc.js",
          "kind": "import-statement"
        }
      ]
    },
    "src/input-to.js": {
      "bytes": 1529,
      "imports": [
        {
          "path": "src/utils/events.js",
          "kind": "import-statement"
        },
        {
          "path": "src/utils/query.js",
          "kind": "import-statement"
        },
        {
          "path": "src/utils/misc.js",
          "kind": "import-statement"
        },
        {
          "path": "src/dynamicBehaviour.js",
          "kind": "import-statement"
        },
        {
          "path": "src/utils/date.js",
          "kind": "import-statement"
        },
        {
          "path": "src/utils/attrs.js",
          "kind": "import-statement"
        }
      ]
    },
    "src/input-file.js": {
      "bytes": 7517,
      "imports": [
        {
          "path": "node_modules/nonchalance/esm/ce.js",
          "kind": "import-statement"
        },
        {
          "path": "node_modules/nonchalance/esm/selector.js",
          "kind": "import-statement"
        },
        {
          "path": "src/utils/events.js",
          "kind": "import-statement"
        },
        {
          "path": "src/utils/misc.js",
          "kind": "import-statement"
        },
        {
          "path": "src/utils/attrs.js",
          "kind": "import-statement"
        }
      ]
    },
    "src/input-toggle.js": {
      "bytes": 2098,
      "imports": [
        {
          "path": "node_modules/nonchalance/esm/ce.js",
          "kind": "import-statement"
        },
        {
          "path": "node_modules/nonchalance/esm/selector.js",
          "kind": "import-statement"
        },
        {
          "path": "src/utils/events.js",
          "kind": "import-statement"
        },
        {
          "path": "src/utils/attrs.js",
          "kind": "import-statement"
        },
        {
          "path": "src/utils/misc.js",
          "kind": "import-statement"
        },
        {
          "path": "src/utils/query.js",
          "kind": "import-statement"
        }
      ]
    },
    "src/input-password.js": {
      "bytes": 740,
      "imports": [
        {
          "path": "node_modules/nonchalance/esm/ce.js",
          "kind": "import-statement"
        },
        {
          "path": "node_modules/nonchalance/esm/selector.js",
          "kind": "import-statement"
        },
        {
          "path": "src/utils/events.js",
          "kind": "import-statement"
        },
        {
          "path": "src/utils/query.js",
          "kind": "import-statement"
        },
        {
          "path": "src/utils/misc.js",
          "kind": "import-statement"
        }
      ]
    },
    "src/input-tel.js": {
      "bytes": 7952,
      "imports": [
        {
          "path": "src/utils/events.js",
          "kind": "import-statement"
        },
        {
          "path": "src/dynamicBehaviour.js",
          "kind": "import-statement"
        },
        {
          "path": "src/utils/misc.js",
          "kind": "import-statement"
        },
        {
          "path": "src/utils/attrs.js",
          "kind": "import-statement"
        },
        {
          "path": "src/utils/str.js",
          "kind": "import-statement"
        }
      ]
    },
    "src/label-dblclick.js": {
      "bytes": 595,
      "imports": [
        {
          "path": "src/dynamicBehaviour.js",
          "kind": "import-statement"
        },
        {
          "path": "src/utils/events.js",
          "kind": "import-statement"
        }
      ]
    },
    "src/textarea-autogrow.js": {
      "bytes": 1151,
      "imports": [
        {
          "path": "src/utils/events.js",
          "kind": "import-statement"
        },
        {
          "path": "src/utils/attrs.js",
          "kind": "import-statement"
        },
        {
          "path": "src/dynamicBehaviour.js",
          "kind": "import-statement"
        },
        {
          "path": "src/utils/misc.js",
          "kind": "import-statement"
        }
      ]
    },
    "src/classes/FormValidator.js": {
      "bytes": 8585,
      "imports": [
        {
          "path": "src/utils/attrs.js",
          "kind": "import-statement"
        },
        {
          "path": "src/utils/events.js",
          "kind": "import-statement"
        },
        {
          "path": "src/utils/misc.js",
          "kind": "import-statement"
        },
        {
          "path": "src/utils/query.js",
          "kind": "import-statement"
        },
        {
          "path": "src/utils/str.js",
          "kind": "import-statement"
        }
      ]
    },
    "src/form.js": {
      "bytes": 8085,
      "imports": [
        {
          "path": "node_modules/nonchalance/esm/ce.js",
          "kind": "import-statement"
        },
        {
          "path": "node_modules/nonchalance/esm/selector.js",
          "kind": "import-statement"
        },
        {
          "path": "src/utils/attrs.js",
          "kind": "import-statement"
        },
        {
          "path": "src/utils/events.js",
          "kind": "import-statement"
        },
        {
          "path": "src/utils/attrs.js",
          "kind": "import-statement"
        },
        {
          "path": "src/utils/misc.js",
          "kind": "import-statement"
        },
        {
          "path": "src/classes/FormValidator.js",
          "kind": "import-statement"
        },
        {
          "path": "src/utils/query.js",
          "kind": "import-statement"
        }
      ]
    },
    "src/calendar.js": {
      "bytes": 15735,
      "imports": [
        {
          "path": "src/dynamicBehaviour.js",
          "kind": "import-statement"
        },
        {
          "path": "src/utils/attrs.js",
          "kind": "import-statement"
        },
        {
          "path": "src/utils/date.js",
          "kind": "import-statement"
        },
        {
          "path": "src/utils/events.js",
          "kind": "import-statement"
        },
        {
          "path": "src/utils/map.js",
          "kind": "import-statement"
        },
        {
          "path": "src/utils/misc.js",
          "kind": "import-statement"
        },
        {
          "path": "src/utils/query.js",
          "kind": "import-statement"
        },
        {
          "path": "src/utils/str.js",
          "kind": "import-statement"
        }
      ]
    },
    "src/input-calendar.js": {
      "bytes": 5389,
      "imports": [
        {
          "path": "node_modules/nonchalance/esm/ce.js",
          "kind": "import-statement"
        },
        {
          "path": "node_modules/nonchalance/esm/selector.js",
          "kind": "import-statement"
        },
        {
          "path": "src/utils/misc.js",
          "kind": "import-statement"
        },
        {
          "path": "src/utils/query.js",
          "kind": "import-statement"
        },
        {
          "path": "src/dynamicBehaviour.js",
          "kind": "import-statement"
        },
        {
          "path": "src/utils/date.js",
          "kind": "import-statement"
        },
        {
          "path": "src/utils/events.js",
          "kind": "import-statement"
        }
      ]
    },
    "src/mark-animated.js": {
      "bytes": 1866,
      "imports": [
        {
          "path": "src/utils/misc.js",
          "kind": "import-statement"
        },
        {
          "path": "src/utils/lazy.js",
          "kind": "import-statement"
        },
        {
          "path": "src/utils/attrs.js",
          "kind": "import-statement"
        },
        {
          "path": "src/utils/map.js",
          "kind": "import-statement"
        },
        {
          "path": "src/dynamicBehaviour.js",
          "kind": "import-statement"
        }
      ]
    },
    "src/tooltip.js": {
      "bytes": 9774,
      "imports": [
        {
          "path": "src/dynamicBehaviour.js",
          "kind": "import-statement"
        },
        {
          "path": "src/utils/attrs.js",
          "kind": "import-statement"
        },
        {
          "path": "src/utils/events.js",
          "kind": "import-statement"
        },
        {
          "path": "src/utils/floating.js",
          "kind": "import-statement"
        },
        {
          "path": "src/utils/map.js",
          "kind": "import-statement"
        },
        {
          "path": "src/utils/misc.js",
          "kind": "import-statement"
        },
        {
          "path": "src/utils/query.js",
          "kind": "import-statement"
        }
      ]
    },
    "src/hx.js": {
      "bytes": 8251,
      "imports": [
        {
          "path": "src/dynamicBehaviour.js",
          "kind": "import-statement"
        },
        {
          "path": "src/utils/attrs.js",
          "kind": "import-statement"
        },
        {
          "path": "src/utils/events.js",
          "kind": "import-statement"
        },
        {
          "path": "src/utils/misc.js",
          "kind": "import-statement"
        },
        {
          "path": "src/utils/query.js",
          "kind": "import-statement"
        },
        {
          "path": "src/utils/date.js",
          "kind": "import-statement"
        },
        {
          "path": "src/utils/map.js",
          "kind": "import-statement"
        }
      ]
    },
    "src/cmd.js": {
      "bytes": 1454,
      "imports": [
        {
          "path": "src/dynamicBehaviour.js",
          "kind": "import-statement"
        },
        {
          "path": "src/utils/events.js",
          "kind": "import-statement"
        },
        {
          "path": "src/utils/misc.js",
          "kind": "import-statement"
        },
        {
          "path": "src/utils/query.js",
          "kind": "import-statement"
        }
      ]
    },
    "builds/full.js": {
      "bytes": 1050,
      "imports": [
        {
          "path": "src/addDialogPolyfill.js",
          "kind": "import-statement"
        },
        {
          "path": "src/behaviour.js",
          "kind": "import-statement"
        },
        {
          "path": "src/button-dialog.js",
          "kind": "import-statement"
        },
        {
          "path": "src/button-toggle.js",
          "kind": "import-statement"
        },
        {
          "path": "src/button-dropdown.js",
          "kind": "import-statement"
        },
        {
          "path": "src/input-limited.js",
          "kind": "import-statement"
        },
        {
          "path": "src/input-to.js",
          "kind": "import-statement"
        },
        {
          "path": "src/input-file.js",
          "kind": "import-statement"
        },
        {
          "path": "src/input-toggle.js",
          "kind": "import-statement"
        },
        {
          "path": "src/input-password.js",
          "kind": "import-statement"
        },
        {
          "path": "src/input-tel.js",
          "kind": "import-statement"
        },
        {
          "path": "src/label-dblclick.js",
          "kind": "import-statement"
        },
        {
          "path": "src/textarea-autogrow.js",
          "kind": "import-statement"
        },
        {
          "path": "src/form.js",
          "kind": "import-statement"
        },
        {
          "path": "src/calendar.js",
          "kind": "import-statement"
        },
        {
          "path": "src/input-calendar.js",
          "kind": "import-statement"
        },
        {
          "path": "src/time-datetime.js",
          "kind": "import-statement"
        },
        {
          "path": "src/span-number.js",
          "kind": "import-statement"
        },
        {
          "path": "src/mark-animated.js",
          "kind": "import-statement"
        },
        {
          "path": "src/tooltip.js",
          "kind": "import-statement"
        },
        {
          "path": "src/hx.js",
          "kind": "import-statement"
        },
        {
          "path": "src/cmd.js",
          "kind": "import-statement"
        },
        {
          "path": "src/dynamicBehaviour.js",
          "kind": "import-statement"
        }
      ]
    },
    "builds/tooltip.js": {
      "bytes": 265,
      "imports": [
        {
          "path": "src/tooltip.js",
          "kind": "import-statement"
        },
        {
          "path": "src/dynamicBehaviour.js",
          "kind": "import-statement"
        }
      ]
    }
  },
  "outputs": {
    "dist/dialog.js": {
      "imports": [],
      "exports": [
        "default"
      ],
      "entryPoint": "builds/dialog.js",
      "inputs": {
        "node_modules/element-notifier/esm/index.js": {
          "bytesInOutput": 451
        },
        "node_modules/qsa-observer/esm/index.js": {
          "bytesInOutput": 892
        },
        "src/utils/map.js": {
          "bytesInOutput": 39
        },
        "src/utils/str.js": {
          "bytesInOutput": 63
        },
        "src/utils/attrs.js": {
          "bytesInOutput": 331
        },
        "src/utils/events.js": {
          "bytesInOutput": 574
        },
        "src/utils/query.js": {
          "bytesInOutput": 132
        },
        "src/utils/misc.js": {
          "bytesInOutput": 1728
        },
        "src/utils/lazy.js": {
          "bytesInOutput": 252
        },
        "src/dynamicBehaviour.js": {
          "bytesInOutput": 509
        },
        "src/addDialogPolyfill.js": {
          "bytesInOutput": 603
        },
        "src/button-dialog.js": {
          "bytesInOutput": 783
        },
        "builds/dialog.js": {
          "bytesInOutput": 58
        }
      },
      "bytes": 6570
    },
    "dist/formatters.js": {
      "imports": [],
      "exports": [
        "default"
      ],
      "entryPoint": "builds/formatters.js",
      "inputs": {
        "src/utils/query.js": {
          "bytesInOutput": 73
        },
        "src/utils/str.js": {
          "bytesInOutput": 127
        },
        "src/utils/misc.js": {
          "bytesInOutput": 1224
        },
        "src/utils/attrs.js": {
          "bytesInOutput": 279
        },
        "src/utils/date.js": {
          "bytesInOutput": 876
        },
        "node_modules/element-notifier/esm/index.js": {
          "bytesInOutput": 451
        },
        "node_modules/qsa-observer/esm/index.js": {
          "bytesInOutput": 898
        },
        "src/utils/map.js": {
          "bytesInOutput": 39
        },
        "src/utils/lazy.js": {
          "bytesInOutput": 252
        },
        "src/dynamicBehaviour.js": {
          "bytesInOutput": 510
        },
        "src/time-datetime.js": {
          "bytesInOutput": 1251
        },
        "src/span-number.js": {
          "bytesInOutput": 571
        },
        "builds/formatters.js": {
          "bytesInOutput": 53
        }
      },
      "bytes": 6760
    },
    "dist/full.js": {
      "imports": [],
      "exports": [
        "default"
      ],
      "entryPoint": "builds/full.js",
      "inputs": {
        "node_modules/element-notifier/esm/index.js": {
          "bytesInOutput": 455
        },
        "node_modules/qsa-observer/esm/index.js": {
          "bytesInOutput": 902
        },
        "src/utils/map.js": {
          "bytesInOutput": 131
        },
        "src/utils/str.js": {
          "bytesInOutput": 540
        },
        "src/utils/attrs.js": {
          "bytesInOutput": 1011
        },
        "src/utils/events.js": {
          "bytesInOutput": 701
        },
        "src/utils/query.js": {
          "bytesInOutput": 190
        },
        "src/utils/misc.js": {
          "bytesInOutput": 3845
        },
        "src/utils/lazy.js": {
          "bytesInOutput": 263
        },
        "src/dynamicBehaviour.js": {
          "bytesInOutput": 517
        },
        "src/addDialogPolyfill.js": {
          "bytesInOutput": 605
        },
        "src/behaviour.js": {
          "bytesInOutput": 454
        },
        "src/button-dialog.js": {
          "bytesInOutput": 789
        },
        "node_modules/custom-function/esm/factory.js": {
          "bytesInOutput": 119
        },
        "node_modules/nonchalance/esm/upgrade.js": {
          "bytesInOutput": 1138
        },
        "node_modules/nonchalance/esm/ce.js": {
          "bytesInOutput": 648
        },
        "node_modules/nonchalance/esm/selector.js": {
          "bytesInOutput": 257
        },
        "src/button-toggle.js": {
          "bytesInOutput": 1166
        },
        "src/utils/floating.js": {
          "bytesInOutput": 2772
        },
        "src/button-dropdown.js": {
          "bytesInOutput": 2252
        },
        "src/input-limited.js": {
          "bytesInOutput": 1530
        },
        "src/utils/date.js": {
          "bytesInOutput": 2023
        },
        "src/input-to.js": {
          "bytesInOutput": 347
        },
        "src/input-file.js": {
          "bytesInOutput": 2124
        },
        "src/input-toggle.js": {
          "bytesInOutput": 699
        },
        "src/input-password.js": {
          "bytesInOutput": 273
        },
        "src/input-tel.js": {
          "bytesInOutput": 4434
        },
        "src/label-dblclick.js": {
          "bytesInOutput": 128
        },
        "src/textarea-autogrow.js": {
          "bytesInOutput": 337
        },
        "src/classes/FormValidator.js": {
          "bytesInOutput": 2539
        },
        "src/form.js": {
          "bytesInOutput": 2012
        },
        "src/calendar.js": {
          "bytesInOutput": 5751
        },
        "src/input-calendar.js": {
          "bytesInOutput": 2425
        },
        "src/time-datetime.js": {
          "bytesInOutput": 1265
        },
        "src/span-number.js": {
          "bytesInOutput": 575
        },
        "src/mark-animated.js": {
          "bytesInOutput": 1136
        },
        "src/tooltip.js": {
          "bytesInOutput": 4494
        },
        "src/hx.js": {
          "bytesInOutput": 2244
        },
        "src/cmd.js": {
          "bytesInOutput": 290
        },
        "builds/full.js": {
          "bytesInOutput": 59
        }
      },
      "bytes": 53750
    },
    "dist/tooltip.js": {
      "imports": [],
      "exports": [
        "default"
      ],
      "entryPoint": "builds/tooltip.js",
      "inputs": {
        "node_modules/element-notifier/esm/index.js": {
          "bytesInOutput": 455
        },
        "node_modules/qsa-observer/esm/index.js": {
          "bytesInOutput": 902
        },
        "src/utils/map.js": {
          "bytesInOutput": 39
        },
        "src/utils/str.js": {
          "bytesInOutput": 129
        },
        "src/utils/attrs.js": {
          "bytesInOutput": 629
        },
        "src/utils/events.js": {
          "bytesInOutput": 608
        },
        "src/utils/query.js": {
          "bytesInOutput": 132
        },
        "src/utils/misc.js": {
          "bytesInOutput": 1659
        },
        "src/utils/lazy.js": {
          "bytesInOutput": 253
        },
        "src/dynamicBehaviour.js": {
          "bytesInOutput": 510
        },
        "src/utils/floating.js": {
          "bytesInOutput": 2753
        },
        "src/tooltip.js": {
          "bytesInOutput": 4478
        },
        "builds/tooltip.js": {
          "bytesInOutput": 53
        }
      },
      "bytes": 12753
    }
  }
}
